immopendata/__init__.py
immopendata/havakalitesi.py
immopendata/iett.py
immopendata/isbike.py
immopendata/ispark.py
immopendata/istac.py
immopendata-0.0.6.dist-info/LICENSE
immopendata-0.0.6.dist-info/METADATA
immopendata-0.0.6.dist-info/WHEEL
immopendata-0.0.6.dist-info/top_level.txt
immopendata-0.0.6.dist-info/RECORD
