Metadata-Version: 2.1
Name: immopendata
Version: 0.0.6
Summary: A small package to use data provided by `Istanbul Metropolitan Municipality(IMM) Open Data Portal`
Author-email: Deniz Gökduman <deniz.gokduman@hotmail.com>
Project-URL: Homepage, https://github.com/gokdumano/immopendata
Project-URL: Bug Tracker, https://github.com/gokdumano/immopendata/issues
Classifier: Programming Language :: Python :: 3
Classifier: License :: OSI Approved :: MIT License
Classifier: Operating System :: OS Independent
Requires-Python: >=3.10
License-File: LICENSE
Requires-Dist: requests
Requires-Dist: xml
